README.md
setup.py
custom_loggers/ColoredFormatter.py
custom_loggers/Colors.py
custom_loggers/CustomLogger.py
custom_loggers/__init__.py
custom_loggers.egg-info/PKG-INFO
custom_loggers.egg-info/SOURCES.txt
custom_loggers.egg-info/dependency_links.txt
custom_loggers.egg-info/top_level.txt