Metadata-Version: 2.1
Name: custom-loggers
Version: 1.1.0
Summary: A Custom Logger Class for creating colored, adding level, other misc features
Home-page: https://github.com/astromness/custom_loggers
Author: Austin Stromness
Author-email: stromnessdevelopment@gmail.com
License: MIT
Download-URL: https://github.com/astromness/custom_loggers/archive/refs/tags/1.1.0.tar.gz
Keywords: logging,colored,loglevel,console,custom
Platform: UNKNOWN
Classifier: Development Status :: 5 - Production/Stable
Classifier: Intended Audience :: Developers
Classifier: Topic :: Software Development
Classifier: License :: OSI Approved :: MIT License
Classifier: Programming Language :: Python :: 3
Classifier: Programming Language :: Python :: 3.9
